examples/__init__.py
examples/codegen_async.py
examples/codegen_sync.py
examples/hackernews_async.py
examples/hackernews_sync.py
llm_scraper_py/__init__.py
llm_scraper_py/index.py
llm_scraper_py/models.py
llm_scraper_py/playwright_js.py
llm_scraper_py/preprocess.py
llm_scraper_py/util.py
llm_scraper_py-0.4.0.dist-info/licenses/LICENSE.md
tests/__init__.py
tests/conftest.py
tests/test_integration_sync.py
tests/test_llm_scraper.py
tests/test_models.py
tests/test_playwright_js.py
tests/test_preprocess.py
tests/test_smoke.py
tests/test_util.py
llm_scraper_py-0.4.0.dist-info/METADATA
llm_scraper_py-0.4.0.dist-info/WHEEL
llm_scraper_py-0.4.0.dist-info/top_level.txt
llm_scraper_py-0.4.0.dist-info/RECORD
