Metadata-Version: 2.4
Name: llm_scraper_py
Version: 0.4.0
Summary: Turn any webpage into structured data using LLMs
Requires-Python: >=3.0
License-File: LICENSE.md
Requires-Dist: pydantic>=2.0
Requires-Dist: playwright>=1.4
Requires-Dist: jsonschema
Requires-Dist: nest_asyncio
Dynamic: license-file
